iq_readout/__init__.py
iq_readout/classifiers.py
iq_readout/metrics.py
iq_readout/pdfs.py
iq_readout/utils.py
iq_readout/plots/__init__.py
iq_readout/plots/metrics.py
iq_readout/plots/shots1d.py
iq_readout/plots/shots2d.py
iq_readout/plots/summary.py
iq_readout/three_state_classifiers/__init__.py
iq_readout/three_state_classifiers/gmda.py
iq_readout/two_state_classifiers/__init__.py
iq_readout/two_state_classifiers/decaylda.py
iq_readout/two_state_classifiers/gmlda.py
iq_readout/two_state_classifiers/maxflda.py
iq_readout-0.1.0.dist-info/LICENSE
iq_readout-0.1.0.dist-info/METADATA
iq_readout-0.1.0.dist-info/WHEEL
iq_readout-0.1.0.dist-info/top_level.txt
iq_readout-0.1.0.dist-info/RECORD
