Metadata-Version: 2.1
Name: iq_readout
Version: 0.1.0
Summary: Classifiers for IQ readout data from qubits
Author-email: Marc Serra Peralta <marcserraperalta@gmail.com>
Maintainer-email: Marc Serra Peralta <marcserraperalta@gmail.com>
License: MIT License
Keywords: IQ,readout,qubit,classifiers,lda
Requires-Python: >=3.8.12
License-File: LICENSE
Requires-Dist: numpy
Requires-Dist: scipy
Requires-Dist: matplotlib
Requires-Dist: pyyaml
Provides-Extra: dev
Requires-Dist: pip-tools ; extra == 'dev'
Requires-Dist: pytest ; extra == 'dev'
Requires-Dist: scalene ; extra == 'dev'
Requires-Dist: black ; extra == 'dev'
Requires-Dist: sphinx ; extra == 'dev'
Requires-Dist: sphinx-rtd-theme ; extra == 'dev'
